{"details": [{"n": "Craig Kennedy, Criminologist", "r": 5.4, "v": 43, "y": "1952", "ec": 26}], "ratings": [{"r": 7.1, "v": 11, "en": "The Lonely Hearts Club", "eid": "tt0550067", "eno": 13, "sno": 1}, {"r": 6.5, "v": 13, "en": "Murder on Stage 9", "eid": "tt0550069", "eno": 15, "sno": 1}, {"r": 6.3, "v": 9, "en": "The Big Shakedown", "eid": "tt0550073", "eno": 1, "sno": 1}, {"r": 5.9, "v": 11, "en": "The Case of Fleming Lewis", "eid": "tt0550074", "eno": 3, "sno": 1}, {"r": 6.6, "v": 9, "en": "The False Claimant", "eid": "tt0550075", "eno": 4, "sno": 1}, {"r": 6.3, "v": 8, "en": "The Strange Destiny", "eid": "tt0550083", "eno": 16, "sno": 1}]}
