{"details": [{"n": "The Newsroom", "r": 8.0, "v": 609, "y": "1996", "ec": 32}], "ratings": [{"r": 7.2, "v": 11, "en": "A Bad Day", "eid": "tt0660323", "eno": 5, "sno": 1}, {"r": 6.7, "v": 10, "en": "Deeper, Deeper", "eid": "tt0660324", "eno": 3, "sno": 1}, {"r": 7.7, "v": 14, "en": "Dinner at Eight", "eid": "tt0660325", "eno": 2, "sno": 1}, {"r": 8.0, "v": 12, "en": "Dis 'n' Dat", "eid": "tt0660326", "eno": 7, "sno": 1}, {"r": 7.8, "v": 17, "en": "Meltdown: Part 1", "eid": "tt0660327", "eno": 10, "sno": 1}, {"r": 7.8, "v": 8, "en": "Meltdown: Part 2", "eid": "tt0660328", "eno": 11, "sno": 1}, {"r": 7.3, "v": 12, "en": "Meltdown: Part 3", "eid": "tt0660329", "eno": 12, "sno": 1}, {"r": 8.0, "v": 8, "en": "Parking", "eid": "tt0660330", "eno": 9, "sno": 1}, {"r": 8.3, "v": 16, "en": "Petty Tyranny", "eid": "tt0660331", "eno": 6, "sno": 1}, {"r": 8.9, "v": 17, "en": "The Campaign", "eid": "tt0660332", "eno": 13, "sno": 1}, {"r": 8.1, "v": 12, "en": "The Kevorkian Joke", "eid": "tt0660333", "eno": 4, "sno": 1}, {"r": 8.1, "v": 17, "en": "The Walking Shoe Incident", "eid": "tt0660334", "eno": 1, "sno": 1}, {"r": 7.5, "v": 8, "en": "Unity", "eid": "tt0660335", "eno": 8, "sno": 1}, {"r": 7.6, "v": 13, "en": "America, America", "eid": "tt0660336", "eno": 1, "sno": 2}, {"r": 7.0, "v": 7, "en": "An Enormous Waste of Time", "eid": "tt0660337", "eno": 4, "sno": 2}, {"r": 7.6, "v": 7, "en": "Baghdad Bound", "eid": "tt0660339", "eno": 5, "sno": 3}, {"r": 8.0, "v": 7, "en": "One of Us", "eid": "tt0660343", "eno": 6, "sno": 2}, {"r": 7.0, "v": 7, "en": "Say Cheese", "eid": "tt0660346", "eno": 12, "sno": 2}, {"r": 7.8, "v": 7, "en": "The Fifty", "eid": "tt1109825", "eno": 8, "sno": 2}]}
