{"details": [{"n": "Code Geass", "r": 8.7, "v": 94247, "y": "2006", "ec": 50}], "ratings": [{"r": 7.6, "v": 1443, "en": "Gakuensai sengen!", "eid": "tt0998609", "eno": 21, "sno": 1}, {"r": 8.4, "v": 1694, "en": "Giasu tai giasu", "eid": "tt0998610", "eno": 14, "sno": 1}, {"r": 8.0, "v": 1517, "en": "Guren mau", "eid": "tt0998611", "eno": 10, "sno": 1}, {"r": 7.7, "v": 1726, "en": "Itsuwari no kurasumeito", "eid": "tt0998612", "eno": 3, "sno": 1}, {"r": 7.9, "v": 1875, "en": "Kakusei no shiroki kishi", "eid": "tt0998613", "eno": 2, "sno": 1}, {"r": 7.8, "v": 1440, "en": "Kami no shima", "eid": "tt0998614", "eno": 19, "sno": 1}, {"r": 8.2, "v": 1504, "en": "Kassai no mao", "eid": "tt0998615", "eno": 15, "sno": 1}, {"r": 8.2, "v": 1461, "en": "Kishi", "eid": "tt0998616", "eno": 17, "sno": 1}, {"r": 8.4, "v": 1657, "en": "Kuro no kishidan", "eid": "tt0998617", "eno": 8, "sno": 1}, {"r": 8.2, "v": 1460, "en": "Kururugi suzaku ni meijiru", "eid": "tt0998618", "eno": 18, "sno": 1}, {"r": 8.1, "v": 1523, "en": "Kyôto kara no shisha", "eid": "tt0998619", "eno": 12, "sno": 1}, {"r": 7.8, "v": 1420, "en": "Kyûshû seneki", "eid": "tt0998620", "eno": 20, "sno": 1}, {"r": 7.6, "v": 1617, "en": "Kôjo to majo", "eid": "tt0998621", "eno": 5, "sno": 1}, {"r": 8.0, "v": 1573, "en": "Kôneria wo ute", "eid": "tt0998622", "eno": 7, "sno": 1}, {"r": 7.7, "v": 2189, "en": "Majin ga umareta hi", "eid": "tt0998623", "eno": 1, "sno": 1}, {"r": 8.5, "v": 1611, "en": "Narita kôbôsen", "eid": "tt0998624", "eno": 11, "sno": 1}, {"r": 7.6, "v": 1529, "en": "Rifurein", "eid": "tt0998625", "eno": 9, "sno": 1}, {"r": 8.3, "v": 1568, "en": "Shârî to jûkô", "eid": "tt0998626", "eno": 13, "sno": 1}, {"r": 8.2, "v": 1757, "en": "Sono na wa zero", "eid": "tt0998627", "eno": 4, "sno": 1}, {"r": 8.0, "v": 1530, "en": "Toraware no nanari", "eid": "tt0998628", "eno": 16, "sno": 1}, {"r": 7.1, "v": 1631, "en": "Ubawareta kamen", "eid": "tt0998629", "eno": 6, "sno": 1}, {"r": 9.5, "v": 3643, "en": "Chizome no euphie", "eid": "tt1016862", "eno": 22, "sno": 1}, {"r": 9.1, "v": 2079, "en": "Semete kanashi mi totomo ni", "eid": "tt1016863", "eno": 23, "sno": 1}, {"r": 8.7, "v": 1651, "en": "Tsuiraku no sutêji", "eid": "tt1019670", "eno": 24, "sno": 1}, {"r": 9.3, "v": 2756, "en": "Zero", "eid": "tt1167167", "eno": 25, "sno": 1}, {"r": 7.8, "v": 1444, "en": "Majin ga mezameru hi", "eid": "tt1267962", "eno": 1, "sno": 2}, {"r": 8.1, "v": 1264, "en": "Shinko kagayaku koku", "eid": "tt1267963", "eno": 10, "sno": 2}, {"r": 8.0, "v": 1269, "en": "Omoi no chikara", "eid": "tt1267964", "eno": 11, "sno": 2}, {"r": 7.2, "v": 1358, "en": "Rabu atakku!", "eid": "tt1267965", "eno": 12, "sno": 2}, {"r": 9.3, "v": 2179, "en": "Kako kara no kikaku", "eid": "tt1267966", "eno": 13, "sno": 2}, {"r": 8.2, "v": 1341, "en": "Nihon dokuritsu keikaku", "eid": "tt1267967", "eno": 2, "sno": 2}, {"r": 8.1, "v": 1293, "en": "Toraware no gakuen", "eid": "tt1267968", "eno": 3, "sno": 2}, {"r": 8.4, "v": 1336, "en": "Gyakushû no shokeidai", "eid": "tt1267969", "eno": 4, "sno": 2}, {"r": 7.8, "v": 1316, "en": "Naito obu raunzu", "eid": "tt1267970", "eno": 5, "sno": 2}, {"r": 8.6, "v": 1382, "en": "Taiheiyô kishû sakusen", "eid": "tt1267971", "eno": 6, "sno": 2}, {"r": 8.3, "v": 1306, "en": "Suterareta kamen", "eid": "tt1267972", "eno": 7, "sno": 2}, {"r": 8.7, "v": 1488, "en": "Hyakuman no kiseki", "eid": "tt1267973", "eno": 8, "sno": 2}, {"r": 8.1, "v": 1275, "en": "Kinshijô no hanayome", "eid": "tt1267974", "eno": 9, "sno": 2}, {"r": 8.8, "v": 1460, "en": "Giasu gari", "eid": "tt1269900", "eno": 14, "sno": 2}, {"r": 9.0, "v": 1622, "en": "C no sekai", "eid": "tt1269901", "eno": 15, "sno": 2}, {"r": 8.6, "v": 1380, "en": "Chôgasshûkoku ketsugi daiichigô", "eid": "tt1269902", "eno": 16, "sno": 2}, {"r": 8.7, "v": 1415, "en": "Tsuchi no aji", "eid": "tt1277058", "eno": 17, "sno": 2}, {"r": 9.3, "v": 1892, "en": "Dainiji Tôkyô taisen", "eid": "tt1279708", "eno": 18, "sno": 2}, {"r": 9.5, "v": 2590, "en": "Uragiri", "eid": "tt1279709", "eno": 19, "sno": 2}, {"r": 8.8, "v": 1488, "en": "Kôtei shikkaku", "eid": "tt1289019", "eno": 20, "sno": 2}, {"r": 9.3, "v": 2185, "en": "Ragunareku no setsuzoku", "eid": "tt1292151", "eno": 21, "sno": 2}, {"r": 8.9, "v": 1666, "en": "Kôtei Rurûshu", "eid": "tt1293374", "eno": 22, "sno": 2}, {"r": 9.0, "v": 1805, "en": "Shunaizeru no kamen", "eid": "tt1293375", "eno": 23, "sno": 2}, {"r": 9.3, "v": 2107, "en": "Damokuresu no sora", "eid": "tt1310120", "eno": 24, "sno": 2}, {"r": 9.9, "v": 13949, "en": "Re;", "eid": "tt1310121", "eno": 25, "sno": 2}]}
