{"details": [{"n": "QAnon: The Search for Q", "r": 5.8, "v": 362, "y": "2021", "ec": 7}], "ratings": [{"r": 6.1, "v": 30, "en": "Why Does Q Exist?", "eid": "tt13848394", "eno": 3, "sno": 1}, {"r": 6.5, "v": 29, "en": "Who is Q?", "eid": "tt13912074", "eno": 2, "sno": 1}, {"r": 6.4, "v": 29, "en": "What is Q?", "eid": "tt13912078", "eno": 1, "sno": 1}, {"r": 6.8, "v": 7, "en": "Killing Q", "eid": "tt21871704", "eno": 1, "sno": 2}, {"r": 6.6, "v": 7, "en": "Conspirituality", "eid": "tt22043346", "eno": 2, "sno": 2}]}
