{"details": [{"n": "We Baby Bears", "r": 5.8, "v": 646, "y": "2022", "ec": 57}], "ratings": [{"r": 7.4, "v": 60, "en": "The Magical Box", "eid": "tt13363556", "eno": 1, "sno": 1}, {"r": 7.2, "v": 25, "en": "Boo-Dunnit", "eid": "tt16315856", "eno": 3, "sno": 1}, {"r": 6.5, "v": 31, "en": "Bears and the Beanstalk", "eid": "tt16315858", "eno": 2, "sno": 1}, {"r": 7.2, "v": 22, "en": "The Little Mer-Bear", "eid": "tt16315860", "eno": 4, "sno": 1}, {"r": 6.1, "v": 26, "en": "Modern-ish Stone Age Family", "eid": "tt16315862", "eno": 5, "sno": 1}, {"r": 6.5, "v": 20, "en": "Meat House", "eid": "tt16315874", "eno": 7, "sno": 1}, {"r": 6.7, "v": 21, "en": "Excalibear", "eid": "tt16315876", "eno": 6, "sno": 1}, {"r": 5.8, "v": 20, "en": "The Pirate Parrot Polly", "eid": "tt16315878", "eno": 8, "sno": 1}, {"r": 6.3, "v": 19, "en": "Baby Bear Genius", "eid": "tt16315880", "eno": 9, "sno": 1}, {"r": 6.8, "v": 22, "en": "Bug City Sleuths", "eid": "tt16315882", "eno": 10, "sno": 1}, {"r": 6.6, "v": 20, "en": "Hashtag Number One Fan", "eid": "tt16315888", "eno": 11, "sno": 1}, {"r": 5.7, "v": 19, "en": "Snow Place Like Home", "eid": "tt16315890", "eno": 12, "sno": 1}, {"r": 6.2, "v": 22, "en": "Fiesta Day", "eid": "tt17423518", "eno": 13, "sno": 1}, {"r": 5.9, "v": 21, "en": "Baba Yaga House", "eid": "tt17423534", "eno": 14, "sno": 1}, {"r": 6.6, "v": 20, "en": "Bears in the Dark", "eid": "tt17519228", "eno": 15, "sno": 1}, {"r": 6.9, "v": 20, "en": "Sheep Bears", "eid": "tt17524502", "eno": 21, "sno": 1}, {"r": 6.4, "v": 19, "en": "Big Trouble Little Babies", "eid": "tt17678512", "eno": 16, "sno": 1}, {"r": 6.6, "v": 20, "en": "Triple T Tigers", "eid": "tt17678546", "eno": 17, "sno": 1}, {"r": 7.1, "v": 21, "en": "Panda's Family", "eid": "tt17678566", "eno": 18, "sno": 1}, {"r": 6.4, "v": 21, "en": "Unica", "eid": "tt17886584", "eno": 20, "sno": 1}, {"r": 4.8, "v": 21, "en": "A Tale of Two Ice Bears", "eid": "tt17886828", "eno": 19, "sno": 1}, {"r": 7.1, "v": 20, "en": "Ice Bear's Pet", "eid": "tt20420530", "eno": 22, "sno": 1}, {"r": 6.8, "v": 18, "en": "Dragon Pests", "eid": "tt20448588", "eno": 23, "sno": 1}, {"r": 7.3, "v": 19, "en": "No Land, All Air!", "eid": "tt20454630", "eno": 24, "sno": 1}, {"r": 7.2, "v": 17, "en": "Tooth Fairy Tech", "eid": "tt20454670", "eno": 25, "sno": 1}, {"r": 6.4, "v": 19, "en": "High Baby Fashion", "eid": "tt21278678", "eno": 26, "sno": 1}, {"r": 7.2, "v": 17, "en": "Teddi Bear", "eid": "tt21279428", "eno": 27, "sno": 1}, {"r": 7.3, "v": 16, "en": "A Gross Worm", "eid": "tt21295398", "eno": 28, "sno": 1}, {"r": 8.1, "v": 19, "en": "A Real Crayon", "eid": "tt21302584", "eno": 29, "sno": 1}, {"r": 7.9, "v": 21, "en": "Witches", "eid": "tt21365672", "eno": 30, "sno": 1}, {"r": 7.5, "v": 17, "en": "Happy Bouncy Fun Town", "eid": "tt22441990", "eno": 31, "sno": 1}, {"r": 8.2, "v": 17, "en": "Back to Our Regular Time Period", "eid": "tt22445088", "eno": 32, "sno": 1}, {"r": 8.1, "v": 18, "en": "Bath on the Nile", "eid": "tt22490888", "eno": 33, "sno": 1}, {"r": 8.2, "v": 19, "en": "Bubble Fields", "eid": "tt22490910", "eno": 34, "sno": 1}, {"r": 7.2, "v": 15, "en": "Who Crashed the RV", "eid": "tt25366224", "eno": 35, "sno": 1}, {"r": 7.0, "v": 13, "en": "Temple Bears", "eid": "tt25366228", "eno": 36, "sno": 1}, {"r": 7.5, "v": 13, "en": "Doll's House", "eid": "tt25366252", "eno": 37, "sno": 1}, {"r": 7.8, "v": 16, "en": "Lighthouse", "eid": "tt25366264", "eno": 38, "sno": 1}, {"r": 8.0, "v": 20, "en": "Little Fallen Star", "eid": "tt27652364", "eno": 39, "sno": 1}, {"r": 7.8, "v": 17, "en": "The Big Wish", "eid": "tt27816364", "eno": 1, "sno": 2}, {"r": 5.3, "v": 17, "en": "Polly's New Crew", "eid": "tt28219396", "eno": 2, "sno": 2}, {"r": 6.9, "v": 10, "en": "Bug City Frame Up", "eid": "tt28219404", "eno": 3, "sno": 2}, {"r": 7.2, "v": 10, "en": "The Great Veggie War", "eid": "tt28219410", "eno": 4, "sno": 2}, {"r": 5.5, "v": 10, "en": "Unica's House", "eid": "tt28625777", "eno": 5, "sno": 2}, {"r": 5.0, "v": 9, "en": "Rexford's Nectar", "eid": "tt28779704", "eno": 6, "sno": 2}, {"r": 6.3, "v": 9, "en": "Grizz's Doc", "eid": "tt28779705", "eno": 7, "sno": 2}, {"r": 5.2, "v": 7, "en": "Triple T Tiger Lilies", "eid": "tt28779708", "eno": 8, "sno": 2}, {"r": 5.6, "v": 7, "en": "After Bedtime", "eid": "tt28779712", "eno": 9, "sno": 2}, {"r": 5.0, "v": 7, "en": "The Parade", "eid": "tt28779715", "eno": 10, "sno": 2}, {"r": 6.9, "v": 10, "en": "The Big Bloom", "eid": "tt28779721", "eno": 11, "sno": 2}]}
