{"details": [{"n": "SkeDJes Sketches", "r": 8.4, "v": 93, "y": "2020", "ec": 53}], "ratings": [{"r": 9.8, "v": 13, "en": "Breaking Up Is Hard to Zoom", "eid": "tt13110818", "eno": 1, "sno": 1}, {"r": 9.6, "v": 8, "en": "Office Dweller", "eid": "tt13110836", "eno": 2, "sno": 1}, {"r": 9.5, "v": 9, "en": "Villain Reopening", "eid": "tt13110850", "eno": 3, "sno": 1}, {"r": 9.0, "v": 8, "en": "Getting That Big Promotion!", "eid": "tt13230366", "eno": 4, "sno": 1}, {"r": 8.8, "v": 13, "en": "Now That's What I Call Spooky Halloween Sound Effects!", "eid": "tt13279436", "eno": 5, "sno": 1}, {"r": 9.2, "v": 9, "en": "Zoom Fight Club", "eid": "tt13293156", "eno": 6, "sno": 1}, {"r": 9.1, "v": 9, "en": "Power Rangers 2020", "eid": "tt13358358", "eno": 7, "sno": 1}, {"r": 9.1, "v": 8, "en": "Christmas Caroling Zoom Bombbers", "eid": "tt13716866", "eno": 8, "sno": 1}, {"r": 8.7, "v": 7, "en": "Game Night", "eid": "tt13814996", "eno": 1, "sno": 2}, {"r": 9.0, "v": 9, "en": "The NFL on Nickelodeon, What's Next?", "eid": "tt13815008", "eno": 2, "sno": 2}, {"r": 9.9, "v": 8, "en": "Fastest Growing Cryptocurrency", "eid": "tt13992574", "eno": 3, "sno": 2}, {"r": 8.8, "v": 8, "en": "Virtual Clothing", "eid": "tt14055448", "eno": 4, "sno": 2}, {"r": 9.2, "v": 5, "en": "Plant Parenthood", "eid": "tt14110668", "eno": 5, "sno": 2}, {"r": 7.8, "v": 6, "en": "Can't Feel My Face (Or I'll Get You)", "eid": "tt14167624", "eno": 6, "sno": 2}, {"r": 10.0, "v": 9, "en": "St. Patrick's Day ZOOM Parade", "eid": "tt14167694", "eno": 7, "sno": 2}, {"r": 7.3, "v": 6, "en": "Totally Safe", "eid": "tt14256464", "eno": 8, "sno": 2}, {"r": 9.3, "v": 7, "en": "Stimmy Checks", "eid": "tt14316998", "eno": 9, "sno": 2}, {"r": 8.6, "v": 5, "en": "Chicago Essential", "eid": "tt14414560", "eno": 11, "sno": 2}, {"r": 9.7, "v": 6, "en": "Happy Earth Day from Big Oil", "eid": "tt14500074", "eno": 13, "sno": 2}]}
