{"details": [{"n": "Angelo Rules", "r": 6.4, "v": 660, "y": "2010", "ec": 221}], "ratings": [{"r": 8.2, "v": 5, "en": "Pop Quiz", "eid": "tt1959730", "eno": 8, "sno": 1}, {"r": 9.2, "v": 12, "en": "Yakking It Up", "eid": "tt1959733", "eno": 3, "sno": 1}, {"r": 7.5, "v": 11, "en": "Cat Box", "eid": "tt2154876", "eno": 2, "sno": 1}, {"r": 8.3, "v": 7, "en": "Battle Underwear", "eid": "tt2205767", "eno": 7, "sno": 1}, {"r": 8.9, "v": 7, "en": "Go Mental Fest", "eid": "tt2205773", "eno": 5, "sno": 1}, {"r": 8.0, "v": 8, "en": "The Greatest Free Sample Ever", "eid": "tt2483716", "eno": 4, "sno": 1}, {"r": 7.7, "v": 7, "en": "Clean Break", "eid": "tt2490214", "eno": 6, "sno": 1}, {"r": 8.2, "v": 6, "en": "Lords of the Prize", "eid": "tt2497164", "eno": 10, "sno": 1}, {"r": 8.0, "v": 6, "en": "Picked Last", "eid": "tt2498818", "eno": 9, "sno": 1}, {"r": 8.6, "v": 7, "en": "Catch that Cat", "eid": "tt3128554", "eno": 22, "sno": 2}, {"r": 7.2, "v": 6, "en": "Book War", "eid": "tt3227026", "eno": 13, "sno": 2}, {"r": 8.8, "v": 11, "en": "Detention", "eid": "tt3233448", "eno": 1, "sno": 1}, {"r": 8.2, "v": 6, "en": "Bullicus Smarticus", "eid": "tt3248110", "eno": 4, "sno": 2}]}
