{"details": [{"n": "Chained Soldier", "r": 6.2, "v": 627, "y": "2024", "ec": 12}], "ratings": [{"r": 6.7, "v": 122, "en": "The Birth, Yuuki, The Awakening", "eid": "tt30195019", "eno": 1, "sno": 1}, {"r": 7.4, "v": 83, "en": "Interest, Shushu, Bare Skin", "eid": "tt30787075", "eno": 2, "sno": 1}, {"r": 7.4, "v": 80, "en": "Encounter, Kyouka, Rampage", "eid": "tt30787080", "eno": 3, "sno": 1}, {"r": 7.6, "v": 68, "en": "Whirlwind, Himari, Roar", "eid": "tt30787082", "eno": 4, "sno": 1}, {"r": 7.7, "v": 64, "en": "Blitz, Sahara, Twinkle", "eid": "tt30789623", "eno": 6, "sno": 1}, {"r": 7.7, "v": 70, "en": "Sisters, Yachiho, Ridicule", "eid": "tt30789624", "eno": 5, "sno": 1}, {"r": 6.4, "v": 66, "en": "United Front, Tenka, Soar", "eid": "tt30789625", "eno": 7, "sno": 1}, {"r": 7.2, "v": 60, "en": "Promise, Nei, Remember", "eid": "tt30789626", "eno": 8, "sno": 1}, {"r": 6.5, "v": 51, "en": "War, Naon, Recite", "eid": "tt30789632", "eno": 10, "sno": 1}, {"r": 6.9, "v": 52, "en": "Reunion, Coco, Lick", "eid": "tt30789633", "eno": 9, "sno": 1}, {"r": 7.3, "v": 43, "en": "Homecoming, New, Resolve", "eid": "tt30789634", "eno": 12, "sno": 1}, {"r": 7.2, "v": 48, "en": "Death Match, Aoba, Excite", "eid": "tt30789635", "eno": 11, "sno": 1}]}
