{"details": [{"n": "Rotten Legacy", "r": 5.7, "v": 546, "y": "2025", "ec": 8}], "ratings": [{"r": 6.8, "v": 27, "en": "Volver", "eid": "tt31656558", "eno": 1, "sno": 1}, {"r": 6.1, "v": 20, "en": "Castigar", "eid": "tt31656559", "eno": 2, "sno": 1}, {"r": 6.4, "v": 18, "en": "Negociar", "eid": "tt31656560", "eno": 3, "sno": 1}, {"r": 6.6, "v": 15, "en": "Despedir", "eid": "tt31656562", "eno": 4, "sno": 1}, {"r": 6.1, "v": 12, "en": "Perdonar", "eid": "tt31656563", "eno": 6, "sno": 1}, {"r": 7.1, "v": 14, "en": "Publicar", "eid": "tt31656564", "eno": 5, "sno": 1}, {"r": 6.1, "v": 13, "en": "Luchar", "eid": "tt31656566", "eno": 7, "sno": 1}, {"r": 6.3, "v": 11, "en": "Decidir", "eid": "tt31656568", "eno": 8, "sno": 1}]}
