{"details": [{"n": "Chaika the Coffin Princess", "r": 7.1, "v": 526, "y": "2014", "ec": 23}], "ratings": [{"r": 7.8, "v": 13, "en": "The Girl Who Bears the Coffin", "eid": "tt4074808", "eno": 1, "sno": 1}, {"r": 7.4, "v": 11, "en": "The Lazy Man's Choice", "eid": "tt4074810", "eno": 2, "sno": 1}, {"r": 7.8, "v": 10, "en": "The Forest Where the Hero Lives", "eid": "tt4074816", "eno": 3, "sno": 1}, {"r": 7.8, "v": 9, "en": "The Dragoon's Wish", "eid": "tt4074824", "eno": 4, "sno": 1}, {"r": 7.5, "v": 8, "en": "The Pursuer and the Pursued", "eid": "tt4074826", "eno": 5, "sno": 1}, {"r": 8.0, "v": 8, "en": "Red and White", "eid": "tt4074828", "eno": 6, "sno": 1}, {"r": 7.6, "v": 8, "en": "The Valley of No Return", "eid": "tt4074832", "eno": 7, "sno": 1}, {"r": 7.2, "v": 8, "en": "Empire of Consolation", "eid": "tt4074834", "eno": 8, "sno": 1}, {"r": 7.8, "v": 9, "en": "The Value of Memories", "eid": "tt4074838", "eno": 9, "sno": 1}, {"r": 7.4, "v": 9, "en": "The False Princess", "eid": "tt4074840", "eno": 11, "sno": 1}, {"r": 7.4, "v": 9, "en": "Fortress in the Sky", "eid": "tt4074842", "eno": 10, "sno": 1}, {"r": 7.9, "v": 9, "en": "Those Left Behind", "eid": "tt4074844", "eno": 12, "sno": 1}, {"r": 8.4, "v": 8, "en": "The Throne That Invites War.", "eid": "tt4634934", "eno": 9, "sno": 2}]}
