{"details": [{"n": "Heated Rivalry", "r": 9.1, "v": 19399, "y": "2025", "ec": 7}], "ratings": [{"r": 9.3, "v": 9866, "en": "Rookies", "eid": "tt38499319", "eno": 1, "sno": 1}, {"r": 9.5, "v": 9814, "en": "Olympians", "eid": "tt38504403", "eno": 2, "sno": 1}, {"r": 9.3, "v": 9572, "en": "Hunter", "eid": "tt38504404", "eno": 3, "sno": 1}, {"r": 9.6, "v": 9774, "en": "Rose", "eid": "tt38504408", "eno": 4, "sno": 1}, {"r": 10.0, "v": 21192, "en": "I'll Believe in Anything", "eid": "tt38504411", "eno": 5, "sno": 1}]}
