{"details": [{"n": "Grigoriy R.", "r": 6.9, "v": 183, "y": "2014", "ec": 8}], "ratings": [{"r": 6.8, "v": 11, "en": "Seriya 3", "eid": "tt4133970", "eno": 3, "sno": 1}, {"r": 7.0, "v": 11, "en": "Seriya 4", "eid": "tt4133972", "eno": 4, "sno": 1}, {"r": 7.2, "v": 14, "en": "Seriya 1", "eid": "tt4133974", "eno": 1, "sno": 1}, {"r": 6.9, "v": 11, "en": "Seriya 2", "eid": "tt4133976", "eno": 2, "sno": 1}, {"r": 6.9, "v": 10, "en": "Seriya 6", "eid": "tt4133978", "eno": 6, "sno": 1}, {"r": 6.7, "v": 11, "en": "Seriya 5", "eid": "tt4133980", "eno": 5, "sno": 1}, {"r": 7.0, "v": 9, "en": "Seriya 7", "eid": "tt4133982", "eno": 7, "sno": 1}, {"r": 7.1, "v": 9, "en": "Seriya 8", "eid": "tt4133984", "eno": 8, "sno": 1}]}
