{"details": [{"n": "Running Man", "r": 5.3, "v": 276, "y": "2014", "ec": 138}], "ratings": [{"r": 5.5, "v": 8, "en": "Lan Ya Bang", "eid": "tt12374766", "eno": 1, "sno": 4}, {"r": 5.4, "v": 8, "en": "Xiao Cheng Da Shi", "eid": "tt12374872", "eno": 1, "sno": 5}, {"r": 5.9, "v": 9, "en": "Vienna Feng Yun", "eid": "tt12375146", "eno": 1, "sno": 6}, {"r": 5.6, "v": 7, "en": "Cheng Shi La Ji", "eid": "tt12375314", "eno": 1, "sno": 7}, {"r": 5.2, "v": 6, "en": "Bai She Chuan Shuo", "eid": "tt4362592", "eno": 1, "sno": 1}, {"r": 4.8, "v": 5, "en": "Dunhuang Da Jie An", "eid": "tt4573236", "eno": 8, "sno": 1}, {"r": 4.4, "v": 5, "en": "Da Mo Gong Zhu Zheng Duo Zhan", "eid": "tt4578534", "eno": 9, "sno": 1}, {"r": 4.4, "v": 5, "en": "Chu Han Zhi Zheng", "eid": "tt4579404", "eno": 10, "sno": 1}, {"r": 5.9, "v": 7, "en": "Chao Neng Li Dian Feng Zhi Zhan", "eid": "tt4582252", "eno": 15, "sno": 1}, {"r": 4.9, "v": 13, "en": "Nü Shen Bao Wei Zhan", "eid": "tt4617328", "eno": 1, "sno": 2}, {"r": 4.0, "v": 5, "en": "Chao Ti Yuan Su Bao Wei Zhan", "eid": "tt4634064", "eno": 2, "sno": 2}, {"r": 4.4, "v": 5, "en": "Da Shu Jue Zhan Hua Mei Nan", "eid": "tt4703616", "eno": 4, "sno": 2}, {"r": 4.4, "v": 5, "en": "Dong Chang Da Zhan Jin Yi Wei", "eid": "tt4703628", "eno": 5, "sno": 2}, {"r": 4.6, "v": 5, "en": "Er tong jie te ji", "eid": "tt4721334", "eno": 7, "sno": 2}, {"r": 5.1, "v": 20, "en": "Zheng jiu Mu Dan", "eid": "tt5164986", "eno": 1, "sno": 3}, {"r": 4.8, "v": 5, "en": "The Princess of the World", "eid": "tt6298100", "eno": 2, "sno": 4}, {"r": 4.0, "v": 5, "en": "Pao Nan Xi'an Mei Shi Bang", "eid": "tt7175472", "eno": 5, "sno": 3}]}
