{"details": [{"n": "Chaos;Child", "r": 5.6, "v": 211, "y": "2017", "ec": 13}], "ratings": [{"r": 7.8, "v": 19, "en": "Chaos;Head", "eid": "tt6819148", "eno": 0, "sno": 1}, {"r": 7.1, "v": 19, "en": "Digital Native", "eid": "tt6819156", "eno": 1, "sno": 1}, {"r": 6.8, "v": 17, "en": "Sumo Sticker", "eid": "tt6819160", "eno": 2, "sno": 1}, {"r": 6.8, "v": 17, "en": "School Festival", "eid": "tt6819166", "eno": 3, "sno": 1}, {"r": 7.0, "v": 17, "en": "Her Words", "eid": "tt6819174", "eno": 4, "sno": 1}, {"r": 7.1, "v": 17, "en": "Gigalomaniacs", "eid": "tt6819180", "eno": 5, "sno": 1}, {"r": 6.8, "v": 17, "en": "Their Resistance", "eid": "tt6819190", "eno": 6, "sno": 1}, {"r": 7.7, "v": 17, "en": "Betrayal", "eid": "tt6819194", "eno": 7, "sno": 1}, {"r": 7.4, "v": 16, "en": "Heads or Tails", "eid": "tt6819200", "eno": 8, "sno": 1}, {"r": 7.1, "v": 15, "en": "Duel", "eid": "tt6819202", "eno": 9, "sno": 1}, {"r": 7.3, "v": 16, "en": "Memories Stalk You from the Past", "eid": "tt6819212", "eno": 10, "sno": 1}, {"r": 7.0, "v": 15, "en": "Takuru Miyashiro", "eid": "tt6819220", "eno": 11, "sno": 1}, {"r": 7.2, "v": 15, "en": "Her Speculation", "eid": "tt6819234", "eno": 12, "sno": 1}]}
