{"details": [{"n": "Harley Quinn", "r": 8.4, "v": 38719, "y": "2019", "ec": 48}], "ratings": [{"r": 8.7, "v": 2049, "en": "Finding Mr. Right", "eid": "tt11272252", "eno": 4, "sno": 1}, {"r": 8.0, "v": 2019, "en": "So, You Need A Crew?", "eid": "tt11272266", "eno": 3, "sno": 1}, {"r": 8.1, "v": 1799, "en": "You're a Damn Good Cop, Jim Gordon", "eid": "tt11272292", "eno": 6, "sno": 1}, {"r": 8.3, "v": 2202, "en": "A High Bar", "eid": "tt11290058", "eno": 2, "sno": 1}, {"r": 7.8, "v": 1910, "en": "Being Harley Quinn", "eid": "tt11368510", "eno": 5, "sno": 1}, {"r": 8.0, "v": 1738, "en": "The Line", "eid": "tt11543486", "eno": 7, "sno": 1}, {"r": 8.2, "v": 1663, "en": "L.O.D.R.S.V.P", "eid": "tt11586546", "eno": 8, "sno": 1}, {"r": 8.3, "v": 1615, "en": "Bensonhurst", "eid": "tt11632574", "eno": 10, "sno": 1}, {"r": 8.0, "v": 1563, "en": "Harley Quinn Highway", "eid": "tt11632576", "eno": 11, "sno": 1}, {"r": 8.7, "v": 1665, "en": "Devil's Snare", "eid": "tt11632578", "eno": 12, "sno": 1}, {"r": 8.6, "v": 1626, "en": "The Final Joke", "eid": "tt11632580", "eno": 13, "sno": 1}, {"r": 8.2, "v": 1638, "en": "A Seat at the Table", "eid": "tt11634144", "eno": 9, "sno": 1}, {"r": 8.1, "v": 1528, "en": "New Gotham", "eid": "tt11839270", "eno": 1, "sno": 2}, {"r": 8.3, "v": 1481, "en": "Riddle U", "eid": "tt12119842", "eno": 2, "sno": 2}, {"r": 7.9, "v": 1448, "en": "Catwoman", "eid": "tt12120726", "eno": 3, "sno": 2}, {"r": 8.7, "v": 1579, "en": "Thawing Hearts", "eid": "tt12158200", "eno": 4, "sno": 2}, {"r": 8.4, "v": 1521, "en": "Batman's Back, Man", "eid": "tt12210750", "eno": 5, "sno": 2}, {"r": 8.8, "v": 1607, "en": "All the Best Inmates Have Daddy Issues", "eid": "tt12246510", "eno": 6, "sno": 2}, {"r": 8.9, "v": 1806, "en": "There's No Place to Go but Down", "eid": "tt12290468", "eno": 7, "sno": 2}, {"r": 8.4, "v": 1445, "en": "Inner (Para) Demons", "eid": "tt12333878", "eno": 8, "sno": 2}, {"r": 8.3, "v": 1474, "en": "Bachelorette", "eid": "tt12374976", "eno": 9, "sno": 2}, {"r": 8.1, "v": 1308, "en": "Dye Hard", "eid": "tt12377106", "eno": 10, "sno": 2}, {"r": 8.6, "v": 1350, "en": "A Fight Worth Fighting For", "eid": "tt12381326", "eno": 11, "sno": 2}, {"r": 8.7, "v": 1345, "en": "Lovers' Quarrel", "eid": "tt12518440", "eno": 12, "sno": 2}, {"r": 8.6, "v": 1479, "en": "The Runaway Bridesmaid", "eid": "tt12526606", "eno": 13, "sno": 2}, {"r": 7.4, "v": 1187, "en": "Harlivy", "eid": "tt13117376", "eno": 1, "sno": 3}, {"r": 8.0, "v": 1070, "en": "There's No Ivy in Team", "eid": "tt21329594", "eno": 2, "sno": 3}, {"r": 7.6, "v": 966, "en": "A Thief, A Mole, An Orgy", "eid": "tt21350684", "eno": 4, "sno": 3}, {"r": 8.0, "v": 1099, "en": "The 83rd Annual Villy Awards", "eid": "tt21350686", "eno": 3, "sno": 3}, {"r": 7.6, "v": 896, "en": "Another Sharkley Adventure", "eid": "tt21350692", "eno": 7, "sno": 3}, {"r": 8.2, "v": 899, "en": "The Horse and the Sparrow", "eid": "tt21350694", "eno": 10, "sno": 3}, {"r": 8.1, "v": 1054, "en": "Joker: The Killing Vote", "eid": "tt21350696", "eno": 6, "sno": 3}, {"r": 9.1, "v": 1273, "en": "Batman Begins Forever", "eid": "tt21350698", "eno": 8, "sno": 3}, {"r": 8.1, "v": 882, "en": "Climax at Jazzapajizza", "eid": "tt21350700", "eno": 9, "sno": 3}, {"r": 7.7, "v": 998, "en": "It's a Swamp Thing", "eid": "tt21350746", "eno": 5, "sno": 3}, {"r": 7.7, "v": 719, "en": "Gotham's Hottest Hotties", "eid": "tt21949956", "eno": 1, "sno": 4}, {"r": 7.7, "v": 1282, "en": "A Very Problematic Valentine's Day Special", "eid": "tt22525032", "eno": 11, "sno": 3}, {"r": 7.6, "v": 676, "en": "B.I.T.C.H.", "eid": "tt28483214", "eno": 2, "sno": 4}, {"r": 7.7, "v": 677, "en": "Icons Only", "eid": "tt28483218", "eno": 3, "sno": 4}, {"r": 7.5, "v": 644, "en": "The First Person to Come Back From a Business Conference Without Chlamydia", "eid": "tt28483225", "eno": 4, "sno": 4}, {"r": 6.7, "v": 651, "en": "Getting Ice Dick, Don't Wait Up", "eid": "tt28483230", "eno": 5, "sno": 4}, {"r": 7.2, "v": 603, "en": "Metamorphosis", "eid": "tt28483234", "eno": 6, "sno": 4}, {"r": 7.5, "v": 609, "en": "The Most Culturally Impactful Film Franchise of All Time", "eid": "tt28483239", "eno": 7, "sno": 4}, {"r": 7.2, "v": 571, "en": "II Buffone", "eid": "tt28483247", "eno": 8, "sno": 4}, {"r": 7.4, "v": 536, "en": "A Potato-Based Cloning Incident", "eid": "tt28483249", "eno": 9, "sno": 4}, {"r": 7.7, "v": 559, "en": "Killer's Block", "eid": "tt28483254", "eno": 10, "sno": 4}, {"r": 8.3, "v": 2668, "en": "'Til Death Do Us Part", "eid": "tt7669548", "eno": 1, "sno": 1}]}
