{"details": [{"n": "The Masked Singer", "r": 5.9, "v": 4696, "y": "2019", "ec": 114}], "ratings": [{"r": 7.5, "v": 98, "en": "The Season Kick off Mask Off: Group A", "eid": "tt10418534", "eno": 1, "sno": 3}, {"r": 7.4, "v": 82, "en": "The Playoffs: Group A", "eid": "tt10418536", "eno": 2, "sno": 3}, {"r": 7.1, "v": 86, "en": "Return of the Masks: Group C", "eid": "tt10538602", "eno": 2, "sno": 2}, {"r": 7.4, "v": 51, "en": "Super Sneak Peek", "eid": "tt10891838", "eno": 0, "sno": 2}, {"r": 7.2, "v": 82, "en": "Return of the Masks: Group D", "eid": "tt10985238", "eno": 3, "sno": 2}, {"r": 7.3, "v": 81, "en": "Once Upon a Mask", "eid": "tt11020732", "eno": 4, "sno": 2}, {"r": 7.4, "v": 73, "en": "Mask Us Anything", "eid": "tt11110852", "eno": 5, "sno": 2}, {"r": 7.5, "v": 71, "en": "Mask-ish", "eid": "tt11131434", "eno": 6, "sno": 2}, {"r": 7.6, "v": 70, "en": "Triumph Over Masks", "eid": "tt11169106", "eno": 7, "sno": 2}, {"r": 7.7, "v": 72, "en": "Mask and You Shall Receive", "eid": "tt11203342", "eno": 8, "sno": 2}, {"r": 7.4, "v": 70, "en": "Clash of the Masks", "eid": "tt11278958", "eno": 9, "sno": 2}, {"r": 7.6, "v": 66, "en": "A Pain in the Mask", "eid": "tt11278964", "eno": 10, "sno": 2}, {"r": 7.8, "v": 72, "en": "Two Masks Take It Off: Holiday Semi-Finals", "eid": "tt11278970", "eno": 11, "sno": 2}, {"r": 6.2, "v": 64, "en": "Road to the Finals", "eid": "tt11278978", "eno": 12, "sno": 2}, {"r": 7.9, "v": 69, "en": "Season Finale: And the Winner Takes It All and Takes It Off", "eid": "tt11372702", "eno": 13, "sno": 2}, {"r": 7.1, "v": 79, "en": "Masking for a Friend: Group A", "eid": "tt11585976", "eno": 3, "sno": 3}, {"r": 7.4, "v": 77, "en": "A Brand New Six Pack: Group B Kickoff!", "eid": "tt11585984", "eno": 4, "sno": 3}, {"r": 7.3, "v": 73, "en": "Mask-Matics: Group B Playoffs", "eid": "tt11585990", "eno": 5, "sno": 3}, {"r": 7.5, "v": 72, "en": "Friends in High Places: Group B Championships", "eid": "tt11777540", "eno": 6, "sno": 3}, {"r": 7.4, "v": 79, "en": "Last But Not Least: Group C Kickoff!", "eid": "tt11814642", "eno": 7, "sno": 3}, {"r": 7.6, "v": 69, "en": "It Never Hurts to Mask: Group C Playoffs", "eid": "tt11872816", "eno": 8, "sno": 3}, {"r": 7.4, "v": 70, "en": "Old Friends, New Clues: Group C Championships", "eid": "tt11909752", "eno": 9, "sno": 3}, {"r": 7.8, "v": 73, "en": "The Super Nine Masked Singer Special: Groups A, B & C", "eid": "tt11916698", "eno": 10, "sno": 3}, {"r": 3.8, "v": 114, "en": "Sing-Along Spectacular", "eid": "tt11916704", "eno": 12, "sno": 3}, {"r": 7.3, "v": 65, "en": "The Mother of All Final Face Offs, Part 1", "eid": "tt11991480", "eno": 11, "sno": 3}, {"r": 7.5, "v": 64, "en": "The Mother of All Final Face Offs, Part 2", "eid": "tt12036978", "eno": 13, "sno": 3}, {"r": 7.5, "v": 60, "en": "The Battle of The Sixes: The Final 6", "eid": "tt12109960", "eno": 14, "sno": 3}, {"r": 7.3, "v": 57, "en": "A Quarter Mask Crisis: The Quarter Finals", "eid": "tt12157604", "eno": 15, "sno": 3}, {"r": 7.4, "v": 55, "en": "A Day In the Mask: The Semi Finals", "eid": "tt12197588", "eno": 16, "sno": 3}, {"r": 4.9, "v": 48, "en": "Road to the Finals", "eid": "tt12246810", "eno": 17, "sno": 3}, {"r": 6.1, "v": 65, "en": "Couldn't Mask For Anything More: The Grand Finale!", "eid": "tt12246818", "eno": 18, "sno": 3}, {"r": 6.2, "v": 48, "en": "Special Season Four Sneak Peek", "eid": "tt12980872", "eno": 0, "sno": 4}, {"r": 8.0, "v": 73, "en": "The Season Premiere - The Masks Return", "eid": "tt12980880", "eno": 1, "sno": 4}, {"r": 7.3, "v": 66, "en": "The Group B Premiere - Six More Masks", "eid": "tt13072992", "eno": 2, "sno": 4}, {"r": 7.6, "v": 60, "en": "The Group A Play Offs - Famous Masked Words", "eid": "tt13103502", "eno": 3, "sno": 4}, {"r": 7.4, "v": 54, "en": "The Group B Play Offs - Cloudy with a Chance of Clues", "eid": "tt13158892", "eno": 4, "sno": 4}, {"r": 6.9, "v": 56, "en": "The Group C Premiere - Masked But Not Least", "eid": "tt13236296", "eno": 5, "sno": 4}, {"r": 7.2, "v": 55, "en": "The Group C Play Offs - Funny You Should Mask", "eid": "tt13315478", "eno": 6, "sno": 4}, {"r": 7.2, "v": 55, "en": "The Group A Finals - The Masked Frontier", "eid": "tt13363922", "eno": 7, "sno": 4}, {"r": 7.0, "v": 53, "en": "The Group B Finals - The Mask Chance Saloon", "eid": "tt13369884", "eno": 8, "sno": 4}, {"r": 7.1, "v": 53, "en": "The Group C Finals - The Masks Give Thanks", "eid": "tt13423982", "eno": 9, "sno": 4}, {"r": 7.5, "v": 52, "en": "The Semi Finals - The Super Six", "eid": "tt13445728", "eno": 10, "sno": 4}, {"r": 4.8, "v": 49, "en": "The Holiday Sing-a-Long", "eid": "tt13508544", "eno": 11, "sno": 4}, {"r": 5.9, "v": 36, "en": "Road to the Finals", "eid": "tt13575064", "eno": 12, "sno": 4}, {"r": 7.3, "v": 51, "en": "The Season 4 Finale - Last Mask Standing", "eid": "tt13575076", "eno": 13, "sno": 4}, {"r": 6.5, "v": 80, "en": "Season 5 Premiere - Return of the Masks", "eid": "tt14128052", "eno": 1, "sno": 5}, {"r": 5.5, "v": 227, "en": "Group B Premiere -- Shamrock and Roll", "eid": "tt14217666", "eno": 2, "sno": 5}, {"r": 7.3, "v": 59, "en": "Group A Wildcard Round -- Enter the Wildcards!", "eid": "tt14217676", "eno": 3, "sno": 5}, {"r": 6.9, "v": 59, "en": "Group B Wildcard Round - Rule of Claw!", "eid": "tt14263466", "eno": 4, "sno": 5}, {"r": 7.1, "v": 54, "en": "Group B Finals - The Ulti 'Mutt' Wildcard!", "eid": "tt14302036", "eno": 5, "sno": 5}, {"r": 7.0, "v": 52, "en": "Group A Finals - In the Nick of Time!", "eid": "tt14327436", "eno": 6, "sno": 5}, {"r": 7.2, "v": 52, "en": "Super 8 - The Plot Chickens!", "eid": "tt14375670", "eno": 7, "sno": 5}, {"r": 7.4, "v": 48, "en": "Super 8 - The Plot Chickens! Part 2", "eid": "tt14495200", "eno": 8, "sno": 5}, {"r": 2.9, "v": 201, "en": "The Sing-A-Long: The Maskie Awards", "eid": "tt14495202", "eno": 9, "sno": 5}, {"r": 7.2, "v": 48, "en": "The Spicy 6 - The Competition Heats Up!", "eid": "tt14495204", "eno": 10, "sno": 5}, {"r": 7.0, "v": 50, "en": "The Quarter Finals - Five Fan Favorites", "eid": "tt14535978", "eno": 11, "sno": 5}, {"r": 7.2, "v": 46, "en": "Semifinals", "eid": "tt14610428", "eno": 12, "sno": 5}, {"r": 7.5, "v": 47, "en": "Finale", "eid": "tt14635252", "eno": 13, "sno": 5}, {"r": 7.1, "v": 60, "en": "2 Night Season Premiere, Part 1: Group A Premiere", "eid": "tt14669226", "eno": 1, "sno": 6}, {"r": 4.2, "v": 29, "en": "Sneak Peek", "eid": "tt15404736", "eno": 0, "sno": 6}, {"r": 7.3, "v": 54, "en": "2 Night Season Premiere, Part 2: Back to School", "eid": "tt15483482", "eno": 2, "sno": 6}, {"r": 7.3, "v": 50, "en": "Group B Premiere: The Masked Gala", "eid": "tt15522002", "eno": 3, "sno": 6}, {"r": 7.4, "v": 48, "en": "House Party", "eid": "tt15560782", "eno": 4, "sno": 6}, {"r": 7.2, "v": 49, "en": "Date Night", "eid": "tt15560786", "eno": 5, "sno": 6}, {"r": 7.1, "v": 47, "en": "Time Warp", "eid": "tt15685436", "eno": 6, "sno": 6}, {"r": 5.4, "v": 50, "en": "All Time Countdown", "eid": "tt15685444", "eno": 7, "sno": 6}, {"r": 6.3, "v": 52, "en": "Giving Thanks", "eid": "tt15816386", "eno": 8, "sno": 6}, {"r": 7.1, "v": 45, "en": "Group A Semi-Final", "eid": "tt15816390", "eno": 9, "sno": 6}, {"r": 7.1, "v": 43, "en": "Group B Semi-Final", "eid": "tt15816394", "eno": 10, "sno": 6}, {"r": 7.6, "v": 42, "en": "Group A Finale", "eid": "tt16270750", "eno": 11, "sno": 6}, {"r": 7.5, "v": 46, "en": "Group B Finale", "eid": "tt16296630", "eno": 12, "sno": 6}, {"r": 6.6, "v": 34, "en": "2 Hour Grand Finale Part 1", "eid": "tt16425050", "eno": 13, "sno": 6}, {"r": 7.2, "v": 32, "en": "2 Hour Grand Finale Part 2", "eid": "tt16425064", "eno": 14, "sno": 6}, {"r": 5.9, "v": 21, "en": "The Masked Singer Christmas Sing Along", "eid": "tt16435938", "eno": 15, "sno": 6}, {"r": 5.9, "v": 56, "en": "Masks Back - The Good, The Bad & The Cuddly - Round 1", "eid": "tt17491230", "eno": 1, "sno": 7}, {"r": 5.5, "v": 32, "en": "Special Sneak Peek", "eid": "tt18272778", "eno": 0, "sno": 7}, {"r": 5.7, "v": 48, "en": "Masks at Dawn - Round 1", "eid": "tt18561152", "eno": 2, "sno": 7}, {"r": 6.2, "v": 48, "en": "The Double Unmasking - Round 1 Finals", "eid": "tt18561156", "eno": 3, "sno": 7}, {"r": 6.2, "v": 51, "en": "Masking For It - The Good, The Bad & The Cuddly - Round 2", "eid": "tt18815278", "eno": 4, "sno": 7}, {"r": 6.7, "v": 47, "en": "Masking for a Duel - Round 2", "eid": "tt18988082", "eno": 5, "sno": 7}, {"r": 6.9, "v": 46, "en": "The Double Mask Off- Round 2 Finals", "eid": "tt19394326", "eno": 6, "sno": 7}, {"r": 2.8, "v": 107, "en": "Don't Mask, Don't Tell-- the Good, the Bad and the Cuddly-- Round 3", "eid": "tt19394382", "eno": 7, "sno": 7}, {"r": 6.1, "v": 48, "en": "The Mask of Least Resistance- Round 3", "eid": "tt19797054", "eno": 8, "sno": 7}, {"r": 6.9, "v": 46, "en": "One Mask Hurrah- Round 3 Finals", "eid": "tt19797070", "eno": 9, "sno": 7}, {"r": 4.7, "v": 40, "en": "Road to the Finals", "eid": "tt19844280", "eno": 10, "sno": 7}, {"r": 5.5, "v": 47, "en": "Season Finale", "eid": "tt19898668", "eno": 11, "sno": 7}, {"r": 7.2, "v": 48, "en": "A Royal Season Premiere", "eid": "tt21871954", "eno": 1, "sno": 8}, {"r": 6.7, "v": 45, "en": "Vegas Night", "eid": "tt22186336", "eno": 2, "sno": 8}, {"r": 7.2, "v": 42, "en": "TV Theme Night", "eid": "tt22186358", "eno": 3, "sno": 8}, {"r": 7.3, "v": 40, "en": "Andrew Lloyd Webber Night", "eid": "tt22394086", "eno": 4, "sno": 8}, {"r": 6.8, "v": 39, "en": "Muppets Night", "eid": "tt22504558", "eno": 5, "sno": 8}, {"r": 6.8, "v": 33, "en": "90's Night", "eid": "tt22853852", "eno": 6, "sno": 8}, {"r": 7.5, "v": 30, "en": "Hall of Fame Night", "eid": "tt22853872", "eno": 7, "sno": 8}, {"r": 6.8, "v": 29, "en": "Comedy Roast Night", "eid": "tt23038820", "eno": 8, "sno": 8}, {"r": 7.5, "v": 26, "en": "Fright Night", "eid": "tt23584832", "eno": 9, "sno": 8}, {"r": 7.1, "v": 24, "en": "Battle of the Semi Finals", "eid": "tt23585748", "eno": 10, "sno": 8}, {"r": 6.1, "v": 22, "en": "Two Hour Epic Final: Part 2", "eid": "tt23585936", "eno": 12, "sno": 8}, {"r": 4.5, "v": 24, "en": "Two Hour Epic Final: Part 1", "eid": "tt23863894", "eno": 11, "sno": 8}, {"r": 7.7, "v": 10, "en": "Seasonal Sing-A-Long Spectacular", "eid": "tt23863912", "eno": 13, "sno": 8}, {"r": 7.0, "v": 209, "en": "Season Premiere: Mask On Face Off", "eid": "tt8787360", "eno": 1, "sno": 1}, {"r": 7.0, "v": 157, "en": "New Masks on the Block", "eid": "tt9347444", "eno": 2, "sno": 1}, {"r": 7.0, "v": 147, "en": "Five Masks No More", "eid": "tt9347558", "eno": 3, "sno": 1}, {"r": 7.1, "v": 138, "en": "Another Mask Bites the Dust", "eid": "tt9347562", "eno": 4, "sno": 1}, {"r": 7.3, "v": 134, "en": "Mix and Masks", "eid": "tt9347568", "eno": 5, "sno": 1}, {"r": 7.1, "v": 122, "en": "Touchy Feely Clues", "eid": "tt9347570", "eno": 6, "sno": 1}, {"r": 8.1, "v": 114, "en": "All Together Now", "eid": "tt9347574", "eno": 7, "sno": 1}, {"r": 7.9, "v": 101, "en": "Semi Finals: Double Unmasking", "eid": "tt9347598", "eno": 8, "sno": 1}, {"r": 7.1, "v": 88, "en": "Road to the Finals", "eid": "tt9347606", "eno": 9, "sno": 1}, {"r": 8.0, "v": 105, "en": "Season Finale: The Final Mask is Lifted", "eid": "tt9347610", "eno": 10, "sno": 1}, {"r": 7.5, "v": 107, "en": "Return of the Masks: Groups A & B", "eid": "tt9691350", "eno": 1, "sno": 2}]}
