{"details": [{"n": "4N1K", "r": 5.1, "v": 320, "y": "2018", "ec": 26}], "ratings": [{"r": 8.1, "v": 9, "en": "I am a princess?", "eid": "tt8628444", "eno": 1, "sno": 1}, {"r": 8.4, "v": 8, "en": "Do you want a challenge?", "eid": "tt8682106", "eno": 2, "sno": 1}, {"r": 8.9, "v": 9, "en": "You lied", "eid": "tt8713256", "eno": 3, "sno": 1}, {"r": 7.0, "v": 6, "en": "Happy time is over", "eid": "tt8759610", "eno": 5, "sno": 1}, {"r": 9.4, "v": 15, "en": "Mysterious boy", "eid": "tt8932458", "eno": 9, "sno": 1}]}
