{"details": [{"n": "2019 Cricket World Cup", "r": 7.6, "v": 67, "y": "2019", "ec": 48}], "ratings": [{"r": 5.3, "v": 6, "en": "2nd Match: West Indies v Pakistan", "eid": "tt10413026", "eno": 2, "sno": 1}, {"r": 5.6, "v": 5, "en": "3rd Match: New Zealand v Sri Lanka", "eid": "tt10413034", "eno": 3, "sno": 1}, {"r": 5.6, "v": 5, "en": "4th Match: Afghanistan v Australia", "eid": "tt10413036", "eno": 4, "sno": 1}, {"r": 6.9, "v": 7, "en": "5th Match: South Africa v Bangladesh", "eid": "tt10413040", "eno": 5, "sno": 1}, {"r": 7.3, "v": 7, "en": "6th Match: England v Pakistan", "eid": "tt10413042", "eno": 6, "sno": 1}, {"r": 5.0, "v": 5, "en": "7th Match: Sri Lanka v Afghanistan", "eid": "tt10413044", "eno": 7, "sno": 1}, {"r": 7.4, "v": 9, "en": "8th Match: India v South Africa", "eid": "tt10413046", "eno": 8, "sno": 1}, {"r": 6.7, "v": 7, "en": "9th Match: New Zealand v Bangladesh", "eid": "tt10413050", "eno": 9, "sno": 1}, {"r": 6.8, "v": 5, "en": "10th Match: Australia v West Indies", "eid": "tt10413052", "eno": 10, "sno": 1}, {"r": 7.6, "v": 7, "en": "12th Match: England v Bangladesh", "eid": "tt10413062", "eno": 12, "sno": 1}, {"r": 7.4, "v": 8, "en": "14th Match: India v Australia", "eid": "tt10413066", "eno": 14, "sno": 1}, {"r": 5.8, "v": 6, "en": "17th Match: Australia v Pakistan", "eid": "tt10476384", "eno": 17, "sno": 1}, {"r": 3.7, "v": 7, "en": "18th Match: India v New Zealand", "eid": "tt10476390", "eno": 18, "sno": 1}, {"r": 7.7, "v": 7, "en": "19th Match: England v West Indies", "eid": "tt10486802", "eno": 19, "sno": 1}, {"r": 6.6, "v": 8, "en": "20th Match: Australia v Sri Lanka", "eid": "tt10491582", "eno": 20, "sno": 1}, {"r": 5.2, "v": 6, "en": "21st Match: South Africa v Afghanistan", "eid": "tt10491596", "eno": 21, "sno": 1}, {"r": 7.5, "v": 6, "en": "23rd Match: Bangladesh v West Indies", "eid": "tt10502556", "eno": 23, "sno": 1}, {"r": 7.0, "v": 6, "en": "24th Match: England v Afghanistan", "eid": "tt10502574", "eno": 24, "sno": 1}, {"r": 6.3, "v": 8, "en": "28th Match: India v Afghanistan", "eid": "tt10502630", "eno": 28, "sno": 1}, {"r": 7.0, "v": 5, "en": "31st Match: Bangladesh v Afghanistan", "eid": "tt10541070", "eno": 31, "sno": 1}, {"r": 7.2, "v": 6, "en": "34th Match: India v West Indies", "eid": "tt10550666", "eno": 34, "sno": 1}, {"r": 6.6, "v": 9, "en": "38th Match: England v India", "eid": "tt10553308", "eno": 38, "sno": 1}, {"r": 6.2, "v": 7, "en": "40th Match: India v Bangladesh", "eid": "tt10553316", "eno": 40, "sno": 1}, {"r": 7.0, "v": 5, "en": "41st Match: England v New Zealand", "eid": "tt10553322", "eno": 41, "sno": 1}, {"r": 5.2, "v": 5, "en": "43rd Match: Bangladesh v Pakistan", "eid": "tt10553334", "eno": 43, "sno": 1}, {"r": 6.0, "v": 6, "en": "44th Match: India v Sri Lanka", "eid": "tt10553336", "eno": 44, "sno": 1}, {"r": 7.2, "v": 10, "en": "1st Semi Final: India v New Zealand", "eid": "tt10601324", "eno": 46, "sno": 1}, {"r": 7.6, "v": 7, "en": "2nd Semi Final: Australia v England", "eid": "tt10601326", "eno": 47, "sno": 1}, {"r": 9.7, "v": 20, "en": "2019 Cricket World Cup Final: England v New Zealand", "eid": "tt10633950", "eno": 48, "sno": 1}, {"r": 7.9, "v": 8, "en": "1st Match: England vs South Africa", "eid": "tt9066418", "eno": 1, "sno": 1}, {"r": 7.0, "v": 13, "en": "22nd Match: India vs Pakistan", "eid": "tt9066428", "eno": 22, "sno": 1}, {"r": 6.8, "v": 5, "en": "32nd Match: Australia vs England", "eid": "tt9066434", "eno": 32, "sno": 1}]}
